.coveragerc
.dockerignore
.gitignore
.gitlab-ci.yml
.pre-commit-config.yaml
LICENSE
MANIFEST.in
README.md
py.typed
pyproject.toml
requirements.txt
requirements_dev.txt
requirements_doc.txt
setup.cfg
setup.py
.github/workflows/github-actions.yml
deker_local_adapters/__init__.py
deker_local_adapters/array_adapter.py
deker_local_adapters/collection_adapter.py
deker_local_adapters/errors.py
deker_local_adapters/factory.py
deker_local_adapters/mixin.py
deker_local_adapters/varray_adapter.py
deker_local_adapters.egg-info/PKG-INFO
deker_local_adapters.egg-info/SOURCES.txt
deker_local_adapters.egg-info/dependency_links.txt
deker_local_adapters.egg-info/requires.txt
deker_local_adapters.egg-info/top_level.txt
deker_local_adapters/storage_adapters/__init__.py
deker_local_adapters/storage_adapters/enums.py
deker_local_adapters/storage_adapters/hdf5/__init__.py
deker_local_adapters/storage_adapters/hdf5/hdf5_options.py
deker_local_adapters/storage_adapters/hdf5/hdf5_storage_adapter.py
docs/Makefile
docs/conf.py
docs/index.rst
docs/make.bat
docs/source/api/array_adapter.rst
docs/source/api/collection_adapter.rst
docs/source/api/enums.rst
docs/source/api/errors.rst
docs/source/api/hdf5_options.rst
docs/source/api/hdf5_storage_adapter.rst
docs/source/api/modules.rst
docs/source/api/varray_adapter.rst
tests/__init__.py
tests/conftest.py
tests/parameters/__init__.py
tests/parameters/array_params.py
tests/parameters/collection_params.py
tests/parameters/common.py
tests/parameters/index_exp_params.py
tests/parameters/schemas_params.py
tests/parameters/uri.py
tests/plugins/__init__.py
tests/plugins/adapter.py
tests/plugins/arrays.py
tests/plugins/collection.py
tests/plugins/factory.py
tests/plugins/schema.py
tests/plugins/subset.py
tests/test_cases/__init__.py
tests/test_cases/test_array_adapter.py
tests/test_cases/test_collection_adapter.py
tests/test_cases/test_collection_options_validation.py
tests/test_cases/test_factory.py
tests/test_cases/test_varray_adapter.py